cgeom/__init__.py
cgeom/algorithms/__init__.py
cgeom/algorithms/_convexhull.py
cgeom/algorithms/_mincircle.py
cgeom/algorithms/_triangulation.py
cgeom/algorithms/_voronoi.py
cgeom/elements/__init__.py
cgeom/elements/elements.py
compute_geometry-0.1.0.dist-info/LICENSE
compute_geometry-0.1.0.dist-info/METADATA
compute_geometry-0.1.0.dist-info/WHEEL
compute_geometry-0.1.0.dist-info/RECORD
