Metadata-Version: 2.1
Name: compute-geometry
Version: 0.1.0
Summary: Computational Geometry Library
Author: Kleyton da Costa
Maintainer: Kleyton da Costa
Maintainer-email: kleyton.vsc@gmail.com
Requires-Python: >=3.8,<4.0.0
Classifier: Programming Language :: Python :: 3
Classifier: Programming Language :: Python :: 3.8
Classifier: Programming Language :: Python :: 3.9
Classifier: Programming Language :: Python :: 3.10
Classifier: Programming Language :: Python :: 3.11
Classifier: Programming Language :: Python :: 3.12
Requires-Dist: seaborn (>=0.11.2)
Requires-Dist: tqdm (>=4.64.1)
